{
    "modules": [
        {
            "config": {
                "position": [
                    1268,
                    381
                ]
            },
            "name": "New Model Object",
            "value": {
                "actionGroup": {
                    "_default0_index": false,
                    "_default1_list": false,
                    "_default2_show": false,
                    "_default3_new_create": false,
                    "_default4_edit_update": false,
                    "_default5_delete": false,
                    "customActions": []
                },
                "name": "Publication",
                "objectsettings": {
                    "addDeletedField": false,
                    "addHiddenField": false,
                    "addStarttimeEndtimeFields": false,
                    "aggregateRoot": true,
                    "categorizable": false,
                    "description": "",
                    "mapToTable": "",
                    "parentClass": "",
                    "sorting": false,
                    "type": "Entity",
                    "uid": "1007324434677"
                },
                "propertyGroup": {
                    "properties": [
                        {
                            "allowedFileTypes": "",
                            "maxItems": "1",
                            "propertyDescription": "",
                            "propertyIsExcludeField": true,
                            "propertyIsL10nModeExclude": true,
                            "propertyIsNullable": false,
                            "propertyIsRequired": true,
                            "propertyName": "extId",
                            "propertyType": "String",
                            "uid": "171479360728"
                        },
                        {
                            "allowedFileTypes": "",
                            "maxItems": "1",
                            "propertyDescription": "",
                            "propertyIsExcludeField": false,
                            "propertyIsL10nModeExclude": true,
                            "propertyIsNullable": false,
                            "propertyIsRequired": true,
                            "propertyName": "slug",
                            "propertyType": "String",
                            "uid": "968833889282"
                        },
                        {
                            "allowedFileTypes": "",
                            "maxItems": "1",
                            "propertyDescription": "",
                            "propertyIsExcludeField": false,
                            "propertyIsL10nModeExclude": true,
                            "propertyIsNullable": false,
                            "propertyIsRequired": true,
                            "propertyName": "type",
                            "propertyType": "String",
                            "uid": "99937585886"
                        },
                        {
                            "allowedFileTypes": "",
                            "maxItems": "1",
                            "propertyDescription": "",
                            "propertyIsExcludeField": false,
                            "propertyIsL10nModeExclude": true,
                            "propertyIsNullable": true,
                            "propertyIsRequired": false,
                            "propertyName": "styles",
                            "propertyType": "String",
                            "uid": "809721846124"
                        },
                        {
                            "allowedFileTypes": "",
                            "maxItems": "1",
                            "propertyDescription": "",
                            "propertyIsExcludeField": false,
                            "propertyIsL10nModeExclude": false,
                            "propertyIsNullable": false,
                            "propertyIsRequired": true,
                            "propertyName": "headerContent",
                            "propertyType": "RichText",
                            "uid": "421531289836"
                        },
                        {
                            "allowedFileTypes": "",
                            "maxItems": "1",
                            "propertyDescription": "",
                            "propertyIsExcludeField": false,
                            "propertyIsL10nModeExclude": false,
                            "propertyIsNullable": true,
                            "propertyIsRequired": false,
                            "propertyName": "badge",
                            "propertyType": "String",
                            "uid": "398551393458"
                        },
                        {
                            "allowedFileTypes": "",
                            "maxItems": "1",
                            "propertyDescription": "",
                            "propertyIsExcludeField": false,
                            "propertyIsL10nModeExclude": false,
                            "propertyIsNullable": false,
                            "propertyIsRequired": true,
                            "propertyName": "title",
                            "propertyType": "String",
                            "uid": "1251271476212"
                        },
                        {
                            "allowedFileTypes": "",
                            "maxItems": "1",
                            "propertyDescription": "",
                            "propertyIsExcludeField": false,
                            "propertyIsL10nModeExclude": false,
                            "propertyIsNullable": false,
                            "propertyIsRequired": true,
                            "propertyName": "content",
                            "propertyType": "RichText",
                            "uid": "848873429708"
                        },
                        {
                            "allowedFileTypes": "",
                            "maxItems": "1",
                            "propertyDescription": "",
                            "propertyIsExcludeField": true,
                            "propertyIsL10nModeExclude": true,
                            "propertyIsNullable": false,
                            "propertyIsRequired": true,
                            "propertyName": "contentCheckSum",
                            "propertyType": "String",
                            "uid": "1424618733459"
                        },
                        {
                            "allowedFileTypes": "",
                            "maxItems": "1",
                            "propertyDescription": "",
                            "propertyIsExcludeField": true,
                            "propertyIsL10nModeExclude": true,
                            "propertyIsNullable": false,
                            "propertyIsRequired": false,
                            "propertyName": "featureImageCheckSum",
                            "propertyType": "String",
                            "uid": "1134293630665"
                        },
                        {
                            "allowedFileTypes": "",
                            "maxItems": "1",
                            "propertyDescription": "",
                            "propertyIsExcludeField": false,
                            "propertyIsL10nModeExclude": false,
                            "propertyIsNullable": true,
                            "propertyIsRequired": false,
                            "propertyName": "kpiMetrics",
                            "propertyType": "String",
                            "uid": "752016724051"
                        }
                    ]
                },
                "relationGroup": {
                    "relations": [
                        {
                            "foreignRelationClass": "",
                            "lazyLoading": true,
                            "propertyIsExcludeField": false,
                            "relationDescription": "",
                            "relationName": "categories",
                            "relationType": "manyToMany",
                            "relationWire": "[wired]",
                            "renderType": "selectMultipleSideBySide",
                            "uid": "1567968144714"
                        },
                        {
                            "foreignRelationClass": "",
                            "lazyLoading": true,
                            "propertyIsExcludeField": false,
                            "relationDescription": "",
                            "relationName": "cover",
                            "relationType": "zeroToOne",
                            "relationWire": "[wired]",
                            "renderType": "selectSingle",
                            "uid": "148489344326"
                        },
                        {
                            "foreignRelationClass": "",
                            "lazyLoading": true,
                            "propertyIsExcludeField": false,
                            "relationDescription": "",
                            "relationName": "header",
                            "relationType": "zeroToOne",
                            "relationWire": "[wired]",
                            "renderType": "selectSingle",
                            "uid": "407250653113"
                        },
                        {
                            "foreignRelationClass": "",
                            "lazyLoading": true,
                            "propertyIsExcludeField": false,
                            "relationDescription": "",
                            "relationName": "tags",
                            "relationType": "manyToMany",
                            "relationWire": "[wired]",
                            "renderType": "selectMultipleSideBySide",
                            "uid": "490570964239"
                        },
                        {
                            "foreignRelationClass": "",
                            "lazyLoading": true,
                            "propertyIsExcludeField": false,
                            "relationDescription": "",
                            "relationName": "portals",
                            "relationType": "manyToMany",
                            "relationWire": "[wired]",
                            "renderType": "selectMultipleSideBySide",
                            "uid": "1061256163358"
                        }
                    ]
                }
            }
        },
        {
            "config": {
                "position": [
                    1060,
                    922
                ]
            },
            "name": "New Model Object",
            "value": {
                "actionGroup": {
                    "_default0_index": false,
                    "_default1_list": false,
                    "_default2_show": false,
                    "_default3_new_create": false,
                    "_default4_edit_update": false,
                    "_default5_delete": false,
                    "customActions": []
                },
                "name": "ContentPart",
                "objectsettings": {
                    "addDeletedField": false,
                    "addHiddenField": false,
                    "addStarttimeEndtimeFields": false,
                    "aggregateRoot": true,
                    "categorizable": false,
                    "description": "",
                    "mapToTable": "",
                    "parentClass": "",
                    "sorting": false,
                    "type": "Entity",
                    "uid": "821988778167"
                },
                "propertyGroup": {
                    "properties": [
                        {
                            "allowedFileTypes": "",
                            "maxItems": "1",
                            "propertyDescription": "",
                            "propertyIsExcludeField": false,
                            "propertyIsL10nModeExclude": false,
                            "propertyIsNullable": false,
                            "propertyIsRequired": true,
                            "propertyName": "title",
                            "propertyType": "String",
                            "uid": "274968221051"
                        },
                        {
                            "allowedFileTypes": "",
                            "maxItems": "1",
                            "propertyDescription": "",
                            "propertyIsExcludeField": false,
                            "propertyIsL10nModeExclude": false,
                            "propertyIsNullable": true,
                            "propertyIsRequired": false,
                            "propertyName": "description",
                            "propertyType": "String",
                            "uid": "172140114309"
                        },
                        {
                            "allowedFileTypes": "",
                            "maxItems": "1",
                            "propertyDescription": "",
                            "propertyIsExcludeField": false,
                            "propertyIsL10nModeExclude": true,
                            "propertyIsNullable": false,
                            "propertyIsRequired": false,
                            "propertyName": "image",
                            "propertyType": "Image",
                            "uid": "868598035353"
                        },
                        {
                            "allowedFileTypes": "",
                            "maxItems": "1",
                            "propertyDescription": "",
                            "propertyIsExcludeField": false,
                            "propertyIsL10nModeExclude": true,
                            "propertyIsNullable": false,
                            "propertyIsRequired": true,
                            "propertyName": "focusX",
                            "propertyType": "Integer",
                            "uid": "615342158821"
                        },
                        {
                            "allowedFileTypes": "",
                            "maxItems": "1",
                            "propertyDescription": "",
                            "propertyIsExcludeField": false,
                            "propertyIsL10nModeExclude": true,
                            "propertyIsNullable": false,
                            "propertyIsRequired": true,
                            "propertyName": "focusY",
                            "propertyType": "Integer",
                            "uid": "669155610816"
                        },
                        {
                            "allowedFileTypes": "",
                            "maxItems": "1",
                            "propertyDescription": "",
                            "propertyIsExcludeField": true,
                            "propertyIsL10nModeExclude": true,
                            "propertyIsNullable": false,
                            "propertyIsRequired": true,
                            "propertyName": "checksum",
                            "propertyType": "String",
                            "uid": "950484481290"
                        }
                    ]
                },
                "relationGroup": {
                    "relations": []
                }
            }
        },
        {
            "config": {
                "position": [
                    544,
                    890
                ]
            },
            "name": "New Model Object",
            "value": {
                "actionGroup": {
                    "_default0_index": false,
                    "_default1_list": false,
                    "_default2_show": false,
                    "_default3_new_create": false,
                    "_default4_edit_update": false,
                    "_default5_delete": false,
                    "customActions": []
                },
                "name": "Category",
                "objectsettings": {
                    "addDeletedField": false,
                    "addHiddenField": false,
                    "addStarttimeEndtimeFields": false,
                    "aggregateRoot": true,
                    "categorizable": false,
                    "description": "",
                    "mapToTable": "",
                    "parentClass": "",
                    "sorting": false,
                    "type": "Entity",
                    "uid": "1348713987867"
                },
                "propertyGroup": {
                    "properties": [
                        {
                            "allowedFileTypes": "",
                            "maxItems": "1",
                            "propertyDescription": "",
                            "propertyIsExcludeField": true,
                            "propertyIsL10nModeExclude": true,
                            "propertyIsNullable": false,
                            "propertyIsRequired": true,
                            "propertyName": "extId",
                            "propertyType": "String",
                            "uid": "707704233185"
                        },
                        {
                            "allowedFileTypes": "",
                            "maxItems": "1",
                            "propertyDescription": "",
                            "propertyIsExcludeField": false,
                            "propertyIsL10nModeExclude": false,
                            "propertyIsNullable": false,
                            "propertyIsRequired": true,
                            "propertyName": "name",
                            "propertyType": "String",
                            "uid": "1170727784242"
                        },
                        {
                            "allowedFileTypes": "",
                            "maxItems": "1",
                            "propertyDescription": "",
                            "propertyIsExcludeField": false,
                            "propertyIsL10nModeExclude": true,
                            "propertyIsNullable": false,
                            "propertyIsRequired": true,
                            "propertyName": "slug",
                            "propertyType": "String",
                            "uid": "743338421432"
                        },
                        {
                            "allowedFileTypes": "",
                            "maxItems": "1",
                            "propertyDescription": "",
                            "propertyIsExcludeField": true,
                            "propertyIsL10nModeExclude": true,
                            "propertyIsNullable": true,
                            "propertyIsRequired": false,
                            "propertyName": "usedAsInterest",
                            "propertyType": "String",
                            "uid": "377325221525"
                        }
                    ]
                },
                "relationGroup": {
                    "relations": [
                        {
                            "foreignRelationClass": "",
                            "lazyLoading": true,
                            "propertyIsExcludeField": false,
                            "relationDescription": "",
                            "relationName": "parent",
                            "relationType": "manyToOne",
                            "relationWire": "[wired]",
                            "renderType": "selectSingle",
                            "uid": "392978938026"
                        }
                    ]
                }
            }
        },
        {
            "config": {
                "position": [
                    460,
                    176
                ]
            },
            "name": "New Model Object",
            "value": {
                "actionGroup": {
                    "_default0_index": false,
                    "_default1_list": false,
                    "_default2_show": false,
                    "_default3_new_create": false,
                    "_default4_edit_update": false,
                    "_default5_delete": false,
                    "customActions": []
                },
                "name": "Tag",
                "objectsettings": {
                    "addDeletedField": false,
                    "addHiddenField": false,
                    "addStarttimeEndtimeFields": false,
                    "aggregateRoot": true,
                    "categorizable": false,
                    "description": "",
                    "mapToTable": "",
                    "parentClass": "",
                    "sorting": false,
                    "type": "Entity",
                    "uid": "186427511436"
                },
                "propertyGroup": {
                    "properties": [
                        {
                            "allowedFileTypes": "",
                            "maxItems": "1",
                            "propertyDescription": "",
                            "propertyIsExcludeField": true,
                            "propertyIsL10nModeExclude": true,
                            "propertyIsNullable": false,
                            "propertyIsRequired": true,
                            "propertyName": "extId",
                            "propertyType": "String",
                            "uid": "1220066893953"
                        },
                        {
                            "allowedFileTypes": "",
                            "maxItems": "1",
                            "propertyDescription": "",
                            "propertyIsExcludeField": false,
                            "propertyIsL10nModeExclude": false,
                            "propertyIsNullable": false,
                            "propertyIsRequired": true,
                            "propertyName": "name",
                            "propertyType": "String",
                            "uid": "751513846981"
                        },
                        {
                            "allowedFileTypes": "",
                            "maxItems": "1",
                            "propertyDescription": "",
                            "propertyIsExcludeField": false,
                            "propertyIsL10nModeExclude": true,
                            "propertyIsNullable": false,
                            "propertyIsRequired": true,
                            "propertyName": "slug",
                            "propertyType": "String",
                            "uid": "348407881918"
                        }
                    ]
                },
                "relationGroup": {
                    "relations": []
                }
            }
        },
        {
            "config": {
                "position": [
                    1730,
                    29
                ]
            },
            "name": "New Model Object",
            "value": {
                "actionGroup": {
                    "_default0_index": false,
                    "_default1_list": false,
                    "_default2_show": false,
                    "_default3_new_create": false,
                    "_default4_edit_update": false,
                    "_default5_delete": false,
                    "customActions": []
                },
                "name": "Portal",
                "objectsettings": {
                    "addDeletedField": false,
                    "addHiddenField": false,
                    "addStarttimeEndtimeFields": false,
                    "aggregateRoot": true,
                    "categorizable": false,
                    "description": "",
                    "mapToTable": "",
                    "parentClass": "",
                    "sorting": false,
                    "type": "Entity",
                    "uid": "1237643798151"
                },
                "propertyGroup": {
                    "properties": [
                        {
                            "allowedFileTypes": "",
                            "maxItems": "1",
                            "propertyDescription": "",
                            "propertyIsExcludeField": true,
                            "propertyIsL10nModeExclude": true,
                            "propertyIsNullable": false,
                            "propertyIsRequired": true,
                            "propertyName": "extId",
                            "propertyType": "String",
                            "uid": "949057143208"
                        },
                        {
                            "allowedFileTypes": "",
                            "maxItems": "1",
                            "propertyDescription": "",
                            "propertyIsExcludeField": false,
                            "propertyIsL10nModeExclude": false,
                            "propertyIsNullable": false,
                            "propertyIsRequired": true,
                            "propertyName": "title",
                            "propertyType": "String",
                            "uid": "433507908299"
                        },
                        {
                            "allowedFileTypes": "",
                            "maxItems": "1",
                            "propertyDescription": "",
                            "propertyIsExcludeField": false,
                            "propertyIsL10nModeExclude": false,
                            "propertyIsNullable": false,
                            "propertyIsRequired": true,
                            "propertyName": "description",
                            "propertyType": "String",
                            "uid": "313633802737"
                        },
                        {
                            "allowedFileTypes": "",
                            "maxItems": "1",
                            "propertyDescription": "",
                            "propertyIsExcludeField": false,
                            "propertyIsL10nModeExclude": true,
                            "propertyIsNullable": false,
                            "propertyIsRequired": false,
                            "propertyName": "headerImage",
                            "propertyType": "Image",
                            "uid": "1469136454877"
                        }
                    ]
                },
                "relationGroup": {
                    "relations": []
                }
            }
        },
        {
            "config": {
                "position": [
                    261,
                    358
                ]
            },
            "name": "New Model Object",
            "value": {
                "actionGroup": {
                    "_default0_index": false,
                    "_default1_list": false,
                    "_default2_show": false,
                    "_default3_new_create": false,
                    "_default4_edit_update": false,
                    "_default5_delete": false,
                    "customActions": []
                },
                "name": "YawaveConnection",
                "objectsettings": {
                    "addDeletedField": true,
                    "addHiddenField": true,
                    "addStarttimeEndtimeFields": true,
                    "aggregateRoot": true,
                    "categorizable": false,
                    "description": "",
                    "mapToTable": "",
                    "parentClass": "",
                    "sorting": false,
                    "type": "Entity",
                    "uid": "941879695312"
                },
                "propertyGroup": {
                    "properties": [
                        {
                            "allowedFileTypes": "",
                            "maxItems": "1",
                            "propertyDescription": "",
                            "propertyIsExcludeField": true,
                            "propertyIsL10nModeExclude": false,
                            "propertyIsNullable": false,
                            "propertyIsRequired": true,
                            "propertyName": "refId",
                            "propertyType": "String",
                            "uid": "1150631562597"
                        },
                        {
                            "allowedFileTypes": "",
                            "maxItems": "1",
                            "propertyDescription": "",
                            "propertyIsExcludeField": true,
                            "propertyIsL10nModeExclude": false,
                            "propertyIsNullable": false,
                            "propertyIsRequired": true,
                            "propertyName": "apiKey",
                            "propertyType": "String",
                            "uid": "795997522253"
                        },
                        {
                            "allowedFileTypes": "",
                            "maxItems": "1",
                            "propertyDescription": "",
                            "propertyIsExcludeField": true,
                            "propertyIsL10nModeExclude": false,
                            "propertyIsNullable": false,
                            "propertyIsRequired": true,
                            "propertyName": "apiSecret",
                            "propertyType": "String",
                            "uid": "39715080342"
                        },
                        {
                            "allowedFileTypes": "",
                            "maxItems": "1",
                            "propertyDescription": "",
                            "propertyIsExcludeField": true,
                            "propertyIsL10nModeExclude": false,
                            "propertyIsNullable": false,
                            "propertyIsRequired": true,
                            "propertyName": "applicationId",
                            "propertyType": "String",
                            "uid": "1595315547693"
                        }
                    ]
                },
                "relationGroup": {
                    "relations": []
                }
            }
        }
    ],
    "properties": {
        "backendModules": [],
        "description": "",
        "emConf": {
            "category": "plugin",
            "custom_category": "",
            "dependsOn": "typo3 => 10.4.0-10.4.99\n",
            "disableLocalization": false,
            "disableVersioning": false,
            "generateDocumentationTemplate": false,
            "generateEditorConfig": false,
            "generateEmptyGitRepository": false,
            "sourceLanguage": "en",
            "state": "alpha",
            "targetVersion": "10.4.0-10.4.99",
            "version": "1.0.0"
        },
        "extensionKey": "yawave_publications",
        "name": "Yawave Adapter",
        "originalExtensionKey": "yawave_publications",
        "originalVendorName": "Interspark",
        "persons": [
            {
                "company": "Interspark GmbH",
                "email": "hannes.pries@interspark.com",
                "name": "Hannes Pries",
                "role": "Developer"
            }
        ],
        "plugins": [
            {
                "actions": {
                    "controllerActionCombinations": "PublicationController => push",
                    "noncacheableActions": "PublicationController => push"
                },
                "description": "",
                "key": "webhook",
                "name": "Webhook"
            }
        ],
        "vendorName": "Interspark"
    },
    "wires": [
        {
            "src": {
                "moduleId": 0,
                "terminal": "relationWire_1",
                "uid": "148489344326"
            },
            "tgt": {
                "moduleId": 1,
                "terminal": "SOURCES",
                "uid": "821988778167"
            }
        },
        {
            "src": {
                "moduleId": 0,
                "terminal": "relationWire_2",
                "uid": "407250653113"
            },
            "tgt": {
                "moduleId": 1,
                "terminal": "SOURCES",
                "uid": "821988778167"
            }
        },
        {
            "src": {
                "moduleId": 0,
                "terminal": "relationWire_3",
                "uid": "490570964239"
            },
            "tgt": {
                "moduleId": 3,
                "terminal": "SOURCES",
                "uid": "186427511436"
            }
        },
        {
            "src": {
                "moduleId": 0,
                "terminal": "relationWire_4",
                "uid": "1061256163358"
            },
            "tgt": {
                "moduleId": 4,
                "terminal": "SOURCES",
                "uid": "1237643798151"
            }
        },
        {
            "src": {
                "moduleId": 0,
                "terminal": "relationWire_0",
                "uid": "1567968144714"
            },
            "tgt": {
                "moduleId": 2,
                "terminal": "SOURCES",
                "uid": "1348713987867"
            }
        },
        {
            "src": {
                "moduleId": 2,
                "terminal": "relationWire_0",
                "uid": "392978938026"
            },
            "tgt": {
                "moduleId": 2,
                "terminal": "SOURCES",
                "uid": "1348713987867"
            }
        }
    ],
    "storagePath": "\/var\/www\/html\/public\/packages\/",
    "log": {
        "last_modified": "2021-10-21 04:17",
        "extension_builder_version": "10.0.1",
        "be_user": " (2)"
    }
}